ampel/content/SVGRecord.py
ampel/model/PlotProperties.py
ampel/plot/SVGBrowser.py
ampel/plot/SVGCollection.py
ampel/plot/SVGLoader.py
ampel/plot/SVGPlot.py
ampel/plot/SVGQuery.py
ampel/plot/T2SVGQuery.py
ampel/plot/utils.py
ampel_plots-0.8.0a0.dist-info/WHEEL
ampel_plots-0.8.0a0.dist-info/METADATA
ampel_plots-0.8.0a0.dist-info/RECORD
